pystylle/__init__.py
pystylle-0.8.dist-info/METADATA
pystylle-0.8.dist-info/WHEEL
pystylle-0.8.dist-info/top_level.txt
pystylle-0.8.dist-info/RECORD
