Metadata-Version: 2.1
Name: pystylle
Version: 0.8
Summary: by billythegoat356, loTus01 and BlueRed
Author-email: <billythegoat356@gmail.com>
License: Eclipse Public License 2.0
